sesconda/__init__.py
sesconda/dlkit.py
ses_conda-2.1.0.dist-info/LICENSE.txt
ses_conda-2.1.0.dist-info/METADATA
ses_conda-2.1.0.dist-info/WHEEL
ses_conda-2.1.0.dist-info/top_level.txt
ses_conda-2.1.0.dist-info/RECORD
