Metadata-Version: 2.1
Name: ses-conda
Version: 2.1.0
Summary: A simple deeplearning kit, implementing the module concept of SES Conda
Home-page: https://github.com/wjz-space/SES-Conda-v2
Author: maomaowjz_ & EricasZ
Author-email: wjz-space@outlook.com
Classifier: Programming Language :: Python :: 3
Classifier: License :: OSI Approved :: MIT License
Classifier: Operating System :: OS Independent
Requires-Python: >=3.0
License-File: LICENSE.txt
Requires-Dist: requests>=2.25.1
Requires-Dist: numpy>=1.19.2
Requires-Dist: scikit-learn>=1.3.0
Requires-Dist: matplotlib
Requires-Dist: torch
Requires-Dist: pandas
